[
  {"_id": 1, "name": "shop1", "coordinates": [52, 51,96]},
  {"_id": 1, "name": "shop1", "coordinates": [52, 51,96]},
  {"_id": 1, "name": "shop1", "coordinates": [52, 51,96]},
  {"_id": 1, "name": "shop1", "coordinates": [52, 51,96]},
  {"_id": 1, "name": "shop1", "coordinates": [52, 51,96]},
  {"_id": 1, "name": "shop1", "coordinates": [52, 51,96]},
  {"_id": 1, "name": "shop1", "coordinates": [52, 51,96]},
  {"_id": 1, "name": "shop1", "coordinates": [52, 51,96]},
  {"_id": 1, "name": "shop1", "coordinates": [52, 51,96]},
  {"_id": 1, "name": "shop1", "coordinates": [52, 51,96]}
]
